{
  "BTCUSDT": {
    "score": 35.0,
    "source": "coingecko",
    "timestamp": "2025-11-16T13:51:12.014712"
  },
  "ETHUSDT": {
    "score": 35.0,
    "source": "coingecko",
    "timestamp": "2025-11-16T13:51:12.564102"
  },
  "SOLUSDT": {
    "score": 35.0,
    "source": "coingecko",
    "timestamp": "2025-11-16T13:51:13.102553"
  },
  "XRPUSDT": {
    "score": 35.0,
    "source": "coingecko",
    "timestamp": "2025-11-16T13:51:13.670999"
  },
  "BNBUSDT": {
    "score": 35.0,
    "source": "coingecko",
    "timestamp": "2025-11-16T13:51:14.240054"
  }
}